integer_pairing/__init__.py
integer_pairing/_bundle.py
integer_pairing/_cantor.py
integer_pairing/_interface.py
integer_pairing/_szudzik.py
LICENSE
integer_pairing-1.0.1.dist-info/LICENSE
integer_pairing-1.0.1.dist-info/WHEEL
integer_pairing-1.0.1.dist-info/METADATA
integer_pairing-1.0.1.dist-info/RECORD
