Metadata-Version: 2.1
Name: integer-pairing
Version: 1.0.1
Summary: 
Home-page: https://github.com/kuco23/integer-pairing/
License: MIT
Keywords: Pairing Functions
Author: Nejc Ševerkar
Author-email: nseverkar@gmail.com
Requires-Python: >=3.10,<4.0
Classifier: License :: OSI Approved :: MIT License
Classifier: Programming Language :: Python :: 3
Classifier: Programming Language :: Python :: 3.10
Project-URL: Repository, https://github.com/kuco23/integer-pairing/
